mmcv/__init__.py
mmcv/_flow_warp_ext.cpython-36m-x86_64-linux-gnu.so
mmcv/version.py
mmcv/arraymisc/__init__.py
mmcv/arraymisc/quantization.py
mmcv/cnn/__init__.py
mmcv/cnn/alexnet.py
mmcv/cnn/resnet.py
mmcv/cnn/vgg.py
mmcv/cnn/bricks/__init__.py
mmcv/cnn/bricks/activation.py
mmcv/cnn/bricks/conv.py
mmcv/cnn/bricks/conv_module.py
mmcv/cnn/bricks/hsigmoid.py
mmcv/cnn/bricks/hswish.py
mmcv/cnn/bricks/non_local.py
mmcv/cnn/bricks/norm.py
mmcv/cnn/bricks/padding.py
mmcv/cnn/bricks/registry.py
mmcv/cnn/bricks/scale.py
mmcv/cnn/bricks/upsample.py
mmcv/cnn/utils/__init__.py
mmcv/cnn/utils/flops_counter.py
mmcv/cnn/utils/weight_init.py
mmcv/fileio/__init__.py
mmcv/fileio/file_client.py
mmcv/fileio/io.py
mmcv/fileio/parse.py
mmcv/fileio/handlers/__init__.py
mmcv/fileio/handlers/base.py
mmcv/fileio/handlers/json_handler.py
mmcv/fileio/handlers/pickle_handler.py
mmcv/fileio/handlers/yaml_handler.py
mmcv/image/__init__.py
mmcv/image/colorspace.py
mmcv/image/geometric.py
mmcv/image/io.py
mmcv/image/photometric.py
mmcv/model_zoo/deprecated.json
mmcv/model_zoo/open_mmlab.json
mmcv/ops/__init__.py
mmcv/ops/bbox.py
mmcv/ops/carafe.py
mmcv/ops/cc_attention.py
mmcv/ops/context_block.py
mmcv/ops/conv_ws.py
mmcv/ops/corner_pool.py
mmcv/ops/deform_conv.py
mmcv/ops/deform_roi_pool.py
mmcv/ops/focal_loss.py
mmcv/ops/generalized_attention.py
mmcv/ops/info.py
mmcv/ops/masked_conv.py
mmcv/ops/merge_cells.py
mmcv/ops/modulated_deform_conv.py
mmcv/ops/nms.py
mmcv/ops/plugin.py
mmcv/ops/point_sample.py
mmcv/ops/psa_mask.py
mmcv/ops/roi_align.py
mmcv/ops/roi_pool.py
mmcv/ops/sync_bn.py
mmcv/ops/wrappers.py
mmcv/parallel/__init__.py
mmcv/parallel/_functions.py
mmcv/parallel/collate.py
mmcv/parallel/data_container.py
mmcv/parallel/data_parallel.py
mmcv/parallel/distributed.py
mmcv/parallel/distributed_deprecated.py
mmcv/parallel/registry.py
mmcv/parallel/scatter_gather.py
mmcv/parallel/utils.py
mmcv/runner/__init__.py
mmcv/runner/base_runner.py
mmcv/runner/checkpoint.py
mmcv/runner/dist_utils.py
mmcv_nightly-1.0rc0.dev20200630.dist-info/LICENSE
mmcv_nightly-1.0rc0.dev20200630.dist-info/METADATA
mmcv_nightly-1.0rc0.dev20200630.dist-info/WHEEL
mmcv_nightly-1.0rc0.dev20200630.dist-info/top_level.txt
mmcv_nightly-1.0rc0.dev20200630.dist-info/RECORD
